pulumi_alicloud_fc_url/__init__.py
pulumi_alicloud_fc_url/_utilities.py
pulumi_alicloud_fc_url/get_trigger_url.py
pulumi_alicloud_fc_url/provider.py
pulumi_alicloud_fc_url/pulumi-plugin.json
pulumi_alicloud_fc_url/py.typed
pulumi_alicloud_fc_url/config/__init__.py
pulumi_alicloud_fc_url/config/__init__.pyi
pulumi_alicloud_fc_url/config/vars.py
pulumi_alicloud_fc_url-0.0.3.dist-info/METADATA
pulumi_alicloud_fc_url-0.0.3.dist-info/WHEEL
pulumi_alicloud_fc_url-0.0.3.dist-info/top_level.txt
pulumi_alicloud_fc_url-0.0.3.dist-info/RECORD
