Metadata-Version: 2.1
Name: pulumi_alicloud_fc_url
Version: 0.0.3
Summary: A Pulumi package for creating and managing alicloud-fc-url cloud resources.
License: Apache-2.0
Project-URL: Homepage, https://www.pulumi.com
Project-URL: Repository, https://github.com/rhysmdnz/pulumi-alicloud-fc-url
Keywords: pulumi,alicloud-fc-url,category/cloud
Requires-Python: >=3.8
Requires-Dist: parver >=0.2.1
Requires-Dist: pulumi <4.0.0,>=3.0.0
Requires-Dist: semver >=2.8.1
Requires-Dist: typing-extensions >=4.11 ; python_version < "3.11"
